fprime_fpp_syntax/__init__.py
fprime_fpp_syntax/__main__.py
fprime_fpp_syntax/fpp-syntax.jar
fprime_fpp_syntax-3.0.0.dist-info/METADATA
fprime_fpp_syntax-3.0.0.dist-info/WHEEL
fprime_fpp_syntax-3.0.0.dist-info/entry_points.txt
fprime_fpp_syntax-3.0.0.dist-info/top_level.txt
fprime_fpp_syntax-3.0.0.dist-info/RECORD
